seekablehttpfile/__init__.py
seekablehttpfile/core.py
seekablehttpfile/py.typed
seekablehttpfile/tests/__init__.py
seekablehttpfile/tests/__main__.py
seekablehttpfile/tests/core.py
seekablehttpfile/tests/live.py
seekablehttpfile-0.1.0.dist-info/LICENSE
seekablehttpfile-0.1.0.dist-info/METADATA
seekablehttpfile-0.1.0.dist-info/WHEEL
seekablehttpfile-0.1.0.dist-info/top_level.txt
seekablehttpfile-0.1.0.dist-info/RECORD
