Metadata-Version: 2.1
Name: seekablehttpfile
Version: 0.1.0
Summary: A lazy-loading, seekable, remote file object using http range requests
Home-page: https://github.com/thatch/seekablehttpfile/
Author: Tim Hatch
Author-email: tim@timhatch.com
License: MIT
Requires-Python: >=3.7
License-File: LICENSE
Requires-Dist: requests
Requires-Dist: keke ; python_version >= "3.8"
Provides-Extra: dev
Requires-Dist: black ==23.12.1 ; extra == 'dev'
Requires-Dist: checkdeps ==0.9.0 ; extra == 'dev'
Requires-Dist: flake8 ==7.0.0 ; extra == 'dev'
Requires-Dist: mypy ==1.8.0 ; extra == 'dev'
Requires-Dist: tox ==4.12.1 ; extra == 'dev'
Requires-Dist: twine ==4.0.2 ; extra == 'dev'
Requires-Dist: ufmt ==2.3.0 ; extra == 'dev'
Requires-Dist: usort ==1.0.7 ; extra == 'dev'
Requires-Dist: wheel ==0.42.0 ; extra == 'dev'
Provides-Extra: test
Requires-Dist: coverage >=6 ; extra == 'test'
